studentgradesconverter/__init__.py
studentgradesconverter/converter.py
studentgradesconverter-0.0.3.dist-info/METADATA
studentgradesconverter-0.0.3.dist-info/WHEEL
studentgradesconverter-0.0.3.dist-info/licenses/LICENSE
studentgradesconverter-0.0.3.dist-info/RECORD
